{
    "resources": [
        {
            "title": "Find me on Twitter",
            "link": "https://twitter.com/kendalmintcode",
            "imageUrl": "https://images.unsplash.com/photo-1552066379-e7bfd22155c5?ixlib=rb-1.2.1&ixid=MnwxMjA3fDB8MHxwaG90by1wYWdlfHx8fGVufDB8fHx8&auto=format&fit=crop&w=387&q=80"
        },
        {
            "title": "Welcome to Ark Labs",
            "link": "https://ark-labs.co.uk",
            "imageUrl": "https://images.unsplash.com/photo-1550898430-483c0280d588?ixlib=rb-1.2.1&ixid=MnwxMjA3fDB8MHxwaG90by1wYWdlfHx8fGVufDB8fHx8&auto=format&fit=crop&w=363&q=80"
        },
        {
            "title": "Some sort of third title",
            "link": "https://twitter.com/kendalmintcode",
            "imageUrl": "https://images.unsplash.com/photo-1616124619460-ff4ed8f4683c?ixlib=rb-1.2.1&ixid=MnwxMjA3fDB8MHxwaG90by1wYWdlfHx8fGVufDB8fHx8&auto=format&fit=crop&w=398&q=80"
        },
        {
            "title": "A personal site perhaps?",
            "link": "https://robkendal.co.uk",
            "imageUrl": "https://images.unsplash.com/photo-1577212017184-80cc0da11082?ixlib=rb-1.2.1&ixid=MnwxMjA3fDB8MHxwaG90by1wYWdlfHx8fGVufDB8fHx8&auto=format&fit=crop&w=387&q=80"
        },
        {
            "title": "Super item number five",
            "link": "https://twitter.com/kendalmintcode",
            "imageUrl": "https://images.unsplash.com/photo-1584275379869-cc7e7c7a3c4b?ixlib=rb-1.2.1&ixid=MnwxMjA3fDB8MHxwaG90by1wYWdlfHx8fGVufDB8fHx8&auto=format&fit=crop&w=435&q=80"
        },
        {
            "title": "Super item number six",
            "link": "https://twitter.com/kendalmintcode",
            "imageUrl": "https://images.unsplash.com/photo-1580969661165-8c2b5d9721b5?ixlib=rb-1.2.1&ixid=MnwxMjA3fDB8MHxwaG90by1wYWdlfHx8fGVufDB8fHx8&auto=format&fit=crop&w=436&q=80"
        },
        {
            "title": "Super item number seven",
            "link": "https://twitter.com/kendalmintcode",
            "imageUrl": "https://images.unsplash.com/photo-1580149959184-c3aaa501a0d4?ixlib=rb-1.2.1&ixid=MnwxMjA3fDB8MHxwaG90by1wYWdlfHx8fGVufDB8fHx8&auto=format&fit=crop&w=387&q=80"
        },
        {
            "title": "Super item number eight",
            "link": "https://twitter.com/kendalmintcode",
            "imageUrl": "https://images.unsplash.com/photo-1550898363-97b48aa83ebe?ixlib=rb-1.2.1&ixid=MnwxMjA3fDB8MHxwaG90by1wYWdlfHx8fGVufDB8fHx8&auto=format&fit=crop&w=870&q=80"
        },
        {
            "title": "Super item number the last",
            "link": "https://twitter.com/kendalmintcode",
            "imageUrl": "https://images.unsplash.com/photo-1600364769293-40c659a6c3c0?ixlib=rb-1.2.1&ixid=MnwxMjA3fDB8MHxwaG90by1wYWdlfHx8fGVufDB8fHx8&auto=format&fit=crop&w=385&q=80"
        }
    ]
}